simtrading/__init__.py
simtrading/backtest_engine/__init__.py
simtrading/backtest_engine/engine.py
simtrading/backtest_engine/analysis/__init__.py
simtrading/backtest_engine/analysis/report.py
simtrading/backtest_engine/analysis/report_utils.py
simtrading/backtest_engine/broker/__init__.py
simtrading/backtest_engine/broker/broker.py
simtrading/backtest_engine/broker/liquidation.py
simtrading/backtest_engine/broker/validator.py
simtrading/backtest_engine/entities/__init__.py
simtrading/backtest_engine/entities/candle.py
simtrading/backtest_engine/entities/enums.py
simtrading/backtest_engine/entities/order_intent.py
simtrading/backtest_engine/entities/portfolio_snapshot.py
simtrading/backtest_engine/entities/position.py
simtrading/backtest_engine/entities/symbol.py
simtrading/backtest_engine/entities/trade.py
simtrading/backtest_engine/portfolio/__init__.py
simtrading/backtest_engine/portfolio/portfolio.py
simtrading/backtest_engine/portfolio/simulator.py
simtrading/backtest_engine/strategy/__init__.py
simtrading/backtest_engine/strategy/base.py
simtrading/backtest_engine/strategy/context.py
simtrading/remote/__init__.py
simtrading/remote/client.py
simtrading/remote/exporter.py
simtrading/remote/provider.py
simtrading/runners/__init__.py
simtrading/runners/custom_runner.py
simtrading/runners/platform_runner.py
simtrading_engine-0.3.4.dist-info/licenses/LICENSE
simtrading_engine-0.3.4.dist-info/METADATA
simtrading_engine-0.3.4.dist-info/WHEEL
simtrading_engine-0.3.4.dist-info/top_level.txt
simtrading_engine-0.3.4.dist-info/RECORD
