Metadata-Version: 2.4
Name: simtrading-engine
Version: 0.3.4
Summary: A Python backtesting engine for trading strategies, designed for SimTrading platform.
Author-email: Arthur Hottier <contact@simtrading.fr>
License: MIT License
Project-URL: Homepage, https://github.com/ArthurHtr/trading-plateform
Project-URL: Bug Tracker, https://github.com/ArthurHtr/trading-plateform/issues
Classifier: Programming Language :: Python :: 3
Classifier: License :: OSI Approved :: MIT License
Classifier: Operating System :: OS Independent
Classifier: Development Status :: 3 - Alpha
Classifier: Intended Audience :: Developers
Classifier: Intended Audience :: Financial and Insurance Industry
Classifier: Topic :: Office/Business :: Financial :: Investment
Requires-Python: >=3.9
License-File: LICENSE
Requires-Dist: requests
Requires-Dist: tqdm
Requires-Dist: pandas
Requires-Dist: numpy
Dynamic: license-file
